parrotjoy/__init__.py
parrotjoy/__main__.py
parrotjoy/audiorecord.py
parrotjoy/camera_cv.py
parrotjoy/cli.py
parrotjoy/draw_sound.py
parrotjoy/main.py
parrotjoy/metronome.py
parrotjoy/resources.py
parrotjoy/tracks.py
parrotjoy/data/aneasterchicken.txt
parrotjoy/data/images/parrotjoy-logo.png
parrotjoy/data/images/letters/a.jpg
parrotjoy/data/images/letters/b.jpg
parrotjoy/data/images/letters/c.jpg
parrotjoy/data/images/letters/d.jpg
parrotjoy/data/images/letters/e.jpg
parrotjoy/data/images/letters/f.jpg
parrotjoy/data/images/letters/g.jpg
parrotjoy/data/images/letters/h.jpg
parrotjoy/data/images/letters/i.jpg
parrotjoy/data/images/letters/j.jpg
parrotjoy/data/images/letters/k.jpg
parrotjoy/data/images/letters/l.jpg
parrotjoy/data/images/letters/m.jpg
parrotjoy/data/images/letters/n.jpg
parrotjoy/data/images/letters/o.jpg
parrotjoy/data/images/letters/p.jpg
parrotjoy/data/images/letters/q.jpg
parrotjoy/data/images/letters/r.jpg
parrotjoy/data/images/letters/s.jpg
parrotjoy/data/images/letters/t.jpg
parrotjoy/data/images/letters/u.jpg
parrotjoy/data/images/letters/v.jpg
parrotjoy/data/images/letters/w.jpg
parrotjoy/data/images/letters/x.jpg
parrotjoy/data/images/letters/y.jpg
parrotjoy/data/images/letters/z.jpg
parrotjoy/scenes/scene.py
parrotjoy/scenes/strawberries.py
parrotjoy/scenes/videosynth.py
parrotjoy/scenes/looper/looper.py
parrotjoy-0.0.1.dev0.dist-info/LICENSE.txt
parrotjoy-0.0.1.dev0.dist-info/METADATA
parrotjoy-0.0.1.dev0.dist-info/WHEEL
parrotjoy-0.0.1.dev0.dist-info/entry_points.txt
parrotjoy-0.0.1.dev0.dist-info/top_level.txt
parrotjoy-0.0.1.dev0.dist-info/RECORD
