Metadata-Version: 2.1
Name: parrotjoy
Version: 0.0.1.dev0
Summary: parrotjoy
Home-page: https://github.com/pygame/parrotjoy
Author: parrotjoy team
Author-email: parrotjoy@pygame.org
Maintainer: parrotjoy team
Maintainer-email: parrotjoy@pygame.org
License: LGPL
Classifier: Development Status :: 3 - Alpha
Classifier: License :: OSI Approved :: GNU Lesser General Public License v2 or later (LGPLv2+)
Classifier: Programming Language :: Python :: 3
Classifier: Programming Language :: Python :: 3.10
Classifier: Topic :: Software Development :: Libraries :: pygame
Classifier: Topic :: Games/Entertainment :: Arcade
License-File: LICENSE.txt
Requires-Dist: pygame
